flet_route_static/__init__.py
flet_route_static/basket.py
flet_route_static/not_found_view.py
flet_route_static/params.py
flet_route_static/routing.py
flet_route_static-0.0.2.dist-info/LICENSE
flet_route_static-0.0.2.dist-info/METADATA
flet_route_static-0.0.2.dist-info/WHEEL
flet_route_static-0.0.2.dist-info/top_level.txt
flet_route_static-0.0.2.dist-info/RECORD
