Metadata-Version: 2.1
Name: flet-route-static
Version: 0.0.2
Summary: This makes it easy to manage multiple views with dynamic routing.
Home-page: https://github.com/saurabhwadekar/flet_route
Author: Saurabh Wadekar, SmokyAce
Maintainer: SmokyAce
Maintainer-email: smokyacetv@gmail.com
License: MIT
Keywords: flet,routing,flet_route_static,routes,flet app,flet-route,flet simple routing
License-File: LICENSE
Requires-Dist: repath
